{"stats":{"minecraft:used":{"minecraft:baked_potato":3},"minecraft:custom":{"minecraft:jump":343,"minecraft:time_since_rest":50352,"minecraft:damage_dealt":10,"minecraft:crouch_one_cm":1218,"minecraft:leave_game":2,"minecraft:play_time":50352,"minecraft:sprint_one_cm":26081,"minecraft:damage_taken":101,"minecraft:time_since_death":50352,"minecraft:walk_one_cm":41957,"minecraft:sneak_time":509,"minecraft:total_world_time":50352,"minecraft:climb_one_cm":2830,"minecraft:fall_one_cm":15736,"minecraft:fly_one_cm":57143}},"DataVersion":3465}